coffy/__init__.py
coffy/cli/__init__.py
coffy/cli/graph_cli.py
coffy/cli/nosql_cli.py
coffy/cli/sql_cli.py
coffy/graph/__init__.py
coffy/graph/atomicity.py
coffy/graph/graph_result.py
coffy/graph/graph_view.py
coffy/graph/graphdb_nx.py
coffy/nosql/__init__.py
coffy/nosql/atomicity.py
coffy/nosql/doclist.py
coffy/nosql/engine.py
coffy/nosql/index_engine.py
coffy/nosql/nosql_view.py
coffy/nosql/query_builder.py
coffy/sql/__init__.py
coffy/sql/engine.py
coffy/sql/orm.py
coffy/sql/sql_view.py
coffy/sql/sqldict.py
coffy-0.2.5.dist-info/licenses/LICENSE
coffy-0.2.5.dist-info/METADATA
coffy-0.2.5.dist-info/WHEEL
coffy-0.2.5.dist-info/entry_points.txt
coffy-0.2.5.dist-info/top_level.txt
coffy-0.2.5.dist-info/RECORD
