Metadata-Version: 2.4
Name: coffy
Version: 0.2.5
Summary: Lightweight local NoSQL, SQL, and Graph embedded database engine
Author: nsarathy
License: MIT
Classifier: Programming Language :: Python :: 3
Classifier: License :: OSI Approved :: MIT License
Classifier: Operating System :: OS Independent
Requires-Python: >=3.7
License-File: LICENSE
Requires-Dist: networkx>=3.0
Requires-Dist: pyvis>=0.3.2
Dynamic: author
Dynamic: classifier
Dynamic: description
Dynamic: description-content-type
Dynamic: license
Dynamic: license-file
Dynamic: requires-dist
Dynamic: requires-python
Dynamic: summary
